AngularJSLibrary/__init__.py
robotframework_angularjs-1.0.0.dist-info/LICENSE
robotframework_angularjs-1.0.0.dist-info/METADATA
robotframework_angularjs-1.0.0.dist-info/WHEEL
robotframework_angularjs-1.0.0.dist-info/top_level.txt
robotframework_angularjs-1.0.0.dist-info/RECORD
