Metadata-Version: 2.1
Name: robotframework-angularjs
Version: 1.0.0
Summary: An AngularJS/Angular extension to Robotframework's SeleniumLibrary
Home-page: https://github.com/MarketSquare/robotframework-angularjs
Author: Zephraph, Ed Manlove
Author-email: emanlove@verizon.net
License: Apache License 2.0
Keywords: robotframework testing testautomation angular selenium webdriver
Classifier: Development Status :: 6 - Mature
Classifier: Framework :: Robot Framework
Classifier: License :: OSI Approved :: Apache Software License
Classifier: Operating System :: OS Independent
Classifier: Programming Language :: Python
Classifier: Programming Language :: Python :: 3
Classifier: Topic :: Software Development :: Testing
License-File: LICENSE
Requires-Dist: robotframework
Requires-Dist: robotframework-seleniumlibrary
